<?xml version="1.0" encoding="UTF-8"?>
<process-definition name="CommonCaseFlow"><start-state name="ACD_START"><description>开  始</description><transition to="CasePreCheckTask" name="案件预审核"/></start-state><task-node name="CasePreCheckTask"><description>CasePreCheckDescription</description><task name="CasePreCheck"><description>案件预审核</description><assignment class="cn.sunline.suncard.trm.wf.TrmAssignmentHandler"/></task><transition to="CasePreCheckDecision"/></task-node><decision name="CasePreCheckDecision"><description>案件预审核决策</description><handler class="cn.sunline.suncard.trm.wf.TrmDecisionHandler"/><transition to="ACC0000002" name="ACC0000002"><description>主管审核</description></transition><transition to="ACC0000001" name="ACC0000001"><description>案件调查建立</description></transition></decision><node name="ACC0000002"><action class="cn.sunline.suncard.trm.wf.TrmWorkFlowActionHandler"/><description>主管审核</description><transition to="ManagerCheckTask"/></node><node name="ACC0000001"><action class="cn.sunline.suncard.trm.wf.TrmWorkFlowActionHandler"/><description>案件调查建立</description><transition to="ReserchSetupTask"/></node><task-node name="ReserchSetupTask"><description>ReserchSetupDescription</description><task name="ReserchSetup"><description>案件调查建立</description><assignment class="cn.sunline.suncard.trm.wf.TrmAssignmentHandler"/></task><transition to="ReserchSetupDecision"/></task-node><decision name="ReserchSetupDecision"><description>案件调查建立决策</description><handler class="cn.sunline.suncard.trm.wf.TrmDecisionHandler"/><transition to="ACC0000006" name="ACC0000006"><description>案件调查</description></transition></decision><node name="ACC0000006"><action class="cn.sunline.suncard.trm.wf.TrmWorkFlowActionHandler"/><description>案件调查</description><transition to="CaseReserchTask"/></node><task-node name="ManagerCheckTask"><description>ManagerCheckDescription</description><task name="ManagerCheck"><description>主管审核</description><assignment class="cn.sunline.suncard.trm.wf.TrmAssignmentHandler"/></task><transition to="ManagerCheckDecision"/></task-node><decision name="ManagerCheckDecision"><description>主管审核决策</description><handler class="cn.sunline.suncard.trm.wf.TrmDecisionHandler"/><transition to="CasePreCheck-ACC0000003" name="CasePreCheck-ACC0000003"><description>直接处理</description></transition><transition to="ACC0000005" name="ACC0000005"><description>恢复之前状态</description></transition></decision><node name="CasePreCheck-ACC0000003"><action class="cn.sunline.suncard.trm.wf.TrmWorkFlowActionHandler"/><description>直接处理</description><transition to="NoReserchProcessTask"/></node><node name="ACC0000005"><action class="cn.sunline.suncard.trm.wf.TrmWorkFlowActionHandler"/><description>恢复之前状态</description><transition to="ReserchSetupTask"/></node><task-node name="CaseReserchTask"><description>CaseReserchDescription</description><task name="CaseReserch"><description>案件调查</description><assignment class="cn.sunline.suncard.trm.wf.TrmAssignmentHandler"/></task><transition to="CaseReserchDecision"/></task-node><decision name="CaseReserchDecision"><description>案件调查决策</description><handler class="cn.sunline.suncard.trm.wf.TrmDecisionHandler"/><transition to="ACC0000007" name="ACC0000007"><description>案件处理</description></transition></decision><node name="ACC0000007"><action class="cn.sunline.suncard.trm.wf.TrmWorkFlowActionHandler"/><description>案件处理</description><transition to="CaseProcessTask"/></node><end-state name="CaseEnd"><description>结  束</description></end-state><task-node name="NoReserchProcessTask"><description>NoReserchProcessDescription</description><task name="NoReserchProcess"><description>直接处理</description><assignment class="cn.sunline.suncard.trm.wf.TrmAssignmentHandler"/></task><transition to="NoReserchProcessDecision"/></task-node><decision name="NoReserchProcessDecision"><description>直接处理决策</description><handler class="cn.sunline.suncard.trm.wf.TrmDecisionHandler"/><transition to="ACC0000008" name="ACC0000008"><description>公安报警</description></transition></decision><node name="ACC0000008"><action class="cn.sunline.suncard.trm.wf.TrmWorkFlowActionHandler"/><description>公安报警</description><transition to="CaseEnd"/></node><task-node name="CaseProcessTask"><description>CaseProcessDescription</description><task name="CaseProcess"><description>案件处理</description><assignment class="cn.sunline.suncard.trm.wf.TrmAssignmentHandler"/></task><transition to="CaseProcessDecision"/></task-node><decision name="CaseProcessDecision"><description>案件处理决策</description><handler class="cn.sunline.suncard.trm.wf.TrmDecisionHandler"/><transition to="ACC0000004" name="ACC0000004"><description>保持预警处理</description></transition></decision><node name="ACC0000004"><action class="cn.sunline.suncard.trm.wf.TrmWorkFlowActionHandler"/><description>保持预警处理</description><transition to="CaseEnd"/></node></process-definition>